Metadata-Version: 2.1
Name: beancount-wacai
Version: 0.1.2
Summary: Import Wacai xlsx to Beancount
Home-page: https://github.com/dallaslu/beancount-wacai
Author: Dallas Lu
Author-email: 914202+dallaslu@users.noreply.github.com
License: UNKNOWN
Project-URL: Issue tracker, https://github.com/dallaslu/beancount-wacai/issues
Platform: UNKNOWN
Classifier: Programming Language :: Python :: 3
Classifier: Operating System :: OS Independent
Classifier: Topic :: Office/Business :: Financial :: Accounting
Requires-Python: >=3.6
